ayeaye/__init__.py
ayeaye/connect.py
ayeaye/connect_resolve.py
ayeaye/exception.py
ayeaye/ignition.py
ayeaye/model.py
ayeaye/model_collection.py
ayeaye/model_collection_original.py
ayeaye/pinnate.py
ayeaye/common_pattern/__init__.py
ayeaye/common_pattern/build_context.py
ayeaye/common_pattern/connect_helper.py
ayeaye/common_pattern/manifest.py
ayeaye/common_pattern/parallel_model_runner.py
ayeaye/connectors/__init__.py
ayeaye/connectors/base.py
ayeaye/connectors/bigquery.py
ayeaye/connectors/csv_connector.py
ayeaye/connectors/elasticsearch_connector.py
ayeaye/connectors/fake.py
ayeaye/connectors/json_connector.py
ayeaye/connectors/kafka_connector.py
ayeaye/connectors/multi_connector.py
ayeaye/connectors/ndjson_connector.py
ayeaye/connectors/parquet_connector.py
ayeaye/connectors/placeholder.py
ayeaye/connectors/restful_connector.py
ayeaye/connectors/sqlalchemy_database.py
ayeaye/connectors/uncooked_connector.py
ayeaye/connectors/engine_type_modifiers/__init__.py
ayeaye/connectors/engine_type_modifiers/abstract_modifier.py
ayeaye/connectors/engine_type_modifiers/smart_open_modifier.py
ayeaye/connectors/engine_type_modifiers/utils.py
ayeaye/runtime/__init__.py
ayeaye/runtime/knowledge.py
ayeaye/runtime/multiprocess.py
ayeaye/runtime/task_message.py
ayeaye-0.1.5.dist-info/licenses/LICENSE
ayeaye-0.1.5.dist-info/licenses/NOTICE
ayeaye-0.1.5.dist-info/METADATA
ayeaye-0.1.5.dist-info/WHEEL
ayeaye-0.1.5.dist-info/top_level.txt
ayeaye-0.1.5.dist-info/RECORD
