Metadata-Version: 2.4
Name: ayeaye
Version: 0.1.5
Summary: An ETL (Extract, Transform, Load) framework
Home-page: https://github.com/Aye-Aye-Dev/AyeAye
Author: Si Parker
Author-email: ayeaye@plogic.co.uk
Project-URL: Bug Tracker, https://github.com/Aye-Aye-Dev/AyeAye/issues
Classifier: Development Status :: 4 - Beta
Classifier: Programming Language :: Python :: 3
Classifier: License :: OSI Approved :: Apache Software License
Classifier: Operating System :: OS Independent
Requires-Python: >=3.6
License-File: LICENSE
License-File: NOTICE
Provides-Extra: api
Requires-Dist: requests; extra == "api"
Provides-Extra: compression
Requires-Dist: smart-open; extra == "compression"
Provides-Extra: aws
Requires-Dist: boto3; extra == "aws"
Requires-Dist: smart-open; extra == "aws"
Dynamic: license-file
